["{\"action\":\"edit\",\"contents\":{\"from\":{\"line\":0,\"ch\":0,\"sticky\":null},\"to\":{\"line\":0,\"ch\":0,\"sticky\":null},\"text\":[\"a\"],\"removed\":[\"\"],\"origin\":\"+input\"}}", "{\"action\":\"edit\",\"contents\":{\"from\":{\"line\":0,\"ch\":1,\"sticky\":null},\"to\":{\"line\":0,\"ch\":1,\"sticky\":null},\"text\":[\"b\"],\"removed\":[\"\"],\"origin\":\"+input\"}}", "{\"action\":\"edit\",\"contents\":{\"from\":{\"line\":0,\"ch\":2,\"sticky\":null},\"to\":{\"line\":0,\"ch\":2,\"sticky\":null},\"text\":[\"\",\"\"],\"removed\":[\"\"],\"origin\":\"+input\"}}", "{\"action\":\"edit\",\"contents\":{\"from\":{\"line\":1,\"ch\":0,\"sticky\":null},\"to\":{\"line\":1,\"ch\":0,\"sticky\":null},\"text\":[\"c\"],\"removed\":[\"\"],\"origin\":\"+input\"}}", "{\"action\":\"edit\",\"contents\":{\"from\":{\"line\":1,\"ch\":1,\"sticky\":null},\"to\":{\"line\":1,\"ch\":1,\"sticky\":null},\"text\":[\"d\"],\"removed\":[\"\"],\"origin\":\"+input\"}}", "{\"action\":\"edit\",\"contents\":{\"from\":{\"line\":1,\"ch\":2,\"sticky\":null},\"to\":{\"line\":1,\"ch\":2,\"sticky\":null},\"text\":[\"\",\"\"],\"removed\":[\"\"],\"origin\":\"+input\"}}", "{\"action\":\"edit\",\"contents\":{\"from\":{\"line\":2,\"ch\":0,\"sticky\":null},\"to\":{\"line\":2,\"ch\":0,\"sticky\":null},\"text\":[\"e\"],\"removed\":[\"\"],\"origin\":\"+input\"}}", "{\"action\":\"edit\",\"contents\":{\"from\":{\"line\":2,\"ch\":1,\"sticky\":null},\"to\":{\"line\":2,\"ch\":1,\"sticky\":null},\"text\":[\"f\"],\"removed\":[\"\"],\"origin\":\"+input\"}}", "{\"action\":\"edit\",\"contents\":{\"from\":{\"line\":2,\"ch\":2,\"sticky\":null},\"to\":{\"line\":2,\"ch\":2,\"sticky\":null},\"text\":[\"\",\"\"],\"removed\":[\"\"],\"origin\":\"+input\"}}", "{\"action\":\"edit\",\"contents\":{\"from\":{\"line\":3,\"ch\":0,\"sticky\":null},\"to\":{\"line\":3,\"ch\":0,\"sticky\":null},\"text\":[\"g\"],\"removed\":[\"\"],\"origin\":\"+input\"}}", "{\"action\":\"edit\",\"contents\":{\"from\":{\"line\":3,\"ch\":1,\"sticky\":null},\"to\":{\"line\":3,\"ch\":1,\"sticky\":null},\"text\":[\"h\"],\"removed\":[\"\"],\"origin\":\"+input\"}}", "{\"action\":\"edit\",\"contents\":{\"from\":{\"line\":0,\"ch\":0,\"sticky\":\"after\",\"xRel\":0},\"to\":{\"line\":3,\"ch\":0,\"sticky\":\"after\",\"xRel\":4},\"text\":[\"\"],\"removed\":[\"ab\",\"cd\",\"ef\",\"\"],\"origin\":\"+delete\"}}"]